socketlock/__init__.py
socketlock/async_lock.py
socketlock/sync_lock.py
socketlock-0.1.0.dist-info/licenses/LICENSE
socketlock-0.1.0.dist-info/METADATA
socketlock-0.1.0.dist-info/WHEEL
socketlock-0.1.0.dist-info/top_level.txt
socketlock-0.1.0.dist-info/RECORD
