Metadata-Version: 2.4
Name: socketlock
Version: 0.1.0
Summary: A robust, secure, and async-friendly process lock using TCP sockets with handshake protocol
Author: Joe Huck
License: MIT
Project-URL: Homepage, https://github.com/comput3/socketlock
Project-URL: Documentation, https://github.com/comput3/socketlock#readme
Project-URL: Repository, https://github.com/comput3/socketlock.git
Project-URL: Issues, https://github.com/comput3/socketlock/issues
Keywords: lock,process,socket,async,asyncio,mutex,synchronization,handshake
Classifier: Development Status :: 4 - Beta
Classifier: Intended Audience :: Developers
Classifier: License :: OSI Approved :: MIT License
Classifier: Operating System :: OS Independent
Classifier: Programming Language :: Python :: 3
Classifier: Programming Language :: Python :: 3.8
Classifier: Programming Language :: Python :: 3.9
Classifier: Programming Language :: Python :: 3.10
Classifier: Programming Language :: Python :: 3.11
Classifier: Programming Language :: Python :: 3.12
Classifier: Topic :: Software Development :: Libraries :: Python Modules
Classifier: Topic :: System :: Networking
Classifier: Framework :: AsyncIO
Requires-Python: >=3.8
License-File: LICENSE
Provides-Extra: dev
Requires-Dist: pytest>=7.0; extra == "dev"
Requires-Dist: pytest-asyncio>=0.21; extra == "dev"
Requires-Dist: pytest-cov>=4.0; extra == "dev"
Requires-Dist: black>=23.0; extra == "dev"
Requires-Dist: isort>=5.0; extra == "dev"
Requires-Dist: mypy>=1.0; extra == "dev"
Requires-Dist: ruff>=0.1; extra == "dev"
Dynamic: license-file
